webpage2md/__init__.py
webpage2md/webpage2md.py
webpage2md-1.0.0.dist-info/METADATA
webpage2md-1.0.0.dist-info/WHEEL
webpage2md-1.0.0.dist-info/entry_points.txt
webpage2md-1.0.0.dist-info/licenses/LICENSE
webpage2md-1.0.0.dist-info/RECORD
