Metadata-Version: 2.4
Name: webpage2md
Version: 1.0.0
Summary: Convert HTML files and web pages to Markdown format
Project-URL: Homepage, https://github.com/nealcaren/webpage2md
Author-email: Neal Caren <neal.caren@unc.edu>
License: MIT License
License-File: LICENSE
Keywords: converter,html,html-to-markdown,markdown,scraping,web
Classifier: License :: OSI Approved :: MIT License
Classifier: Programming Language :: Python
Classifier: Programming Language :: Python :: 3
Requires-Python: >=3.7
Requires-Dist: beautifulsoup4
Requires-Dist: httpx
Requires-Dist: pypandoc
Requires-Dist: pytest-playwright
